nuvo_serial/__init__.py
nuvo_serial/configuration.py
nuvo_serial/connection.py
nuvo_serial/const.py
nuvo_serial/exceptions.py
nuvo_serial/grand_concerto_essentia_g.py
nuvo_serial/message.py
nuvo_serial/nuvo_typing.py
nuvo_serial-0.5.3.dist-info/LICENSE
nuvo_serial-0.5.3.dist-info/METADATA
nuvo_serial-0.5.3.dist-info/WHEEL
nuvo_serial-0.5.3.dist-info/RECORD
