Metadata-Version: 2.1
Name: nuvo-serial
Version: 0.5.3
Summary: Python API implementing the Nuvo Grand Concerto/Essentia G multi-zone audio amplifier serial control protocol
Home-page: https://github.com/sprocket-9/nuvo-serial
License: MIT
Author: sprocket-9
Author-email: sprocketnumber9@gmail.com
Requires-Python: >=3.8,<4.0
Classifier: License :: OSI Approved :: MIT License
Classifier: Programming Language :: Python :: 3
Classifier: Programming Language :: Python :: 3.8
Classifier: Programming Language :: Python :: 3.9
Classifier: Programming Language :: Python :: 3.10
Classifier: Programming Language :: Python :: 3.11
Classifier: Programming Language :: Python :: 3.12
Classifier: Programming Language :: Python :: 3.13
Requires-Dist: icontract (>=2.4)
Requires-Dist: pyserial (>=3.5)
Requires-Dist: pyserial-asyncio-fast (>=0.14)
Requires-Dist: typeguard (>=2.10,<3.0)
Project-URL: Repository, https://github.com/sprocket-9/nuvo-serial
